edc_pdf_reports/__init__.py
edc_pdf_reports/apps.py
edc_pdf_reports/crf_pdf_report.py
edc_pdf_reports/model_mixins.py
edc_pdf_reports/numbered_canvas.py
edc_pdf_reports/report.py
edc_pdf_reports/urls.py
edc_pdf_reports/utils.py
edc_pdf_reports/admin/__init__.py
edc_pdf_reports/admin/actions.py
edc_pdf_reports/admin/modeladmin_mixins.py
edc_pdf_reports/flowables/__init__.py
edc_pdf_reports/flowables/checkbox.py
edc_pdf_reports/flowables/textbox.py
edc_pdf_reports/flowables/textfield.py
edc_pdf_reports/static/edc_pdf_reports/clinicedc_logo.jpg
edc_pdf_reports/templates/edc_pdf_reports/pdf_button.html
edc_pdf_reports/templates/edc_pdf_reports/pdf_intermediate_edc.html
edc_pdf_reports/templates/edc_pdf_reports/pdf_intermediate_generic.html
edc_pdf_reports/tests/__init__.py
edc_pdf_reports/tests/my_report.py
edc_pdf_reports/tests/test_report.py
edc_pdf_reports/tests/test_settings.py
edc_pdf_reports/tests/etc/user-aes-local.key
edc_pdf_reports/tests/etc/user-aes-restricted.key
edc_pdf_reports/tests/etc/user-rsa-local-private.pem
edc_pdf_reports/tests/etc/user-rsa-local-public.pem
edc_pdf_reports/tests/etc/user-rsa-restricted-private.pem
edc_pdf_reports/tests/etc/user-rsa-restricted-public.pem
edc_pdf_reports/tests/etc/user-salt-local.key
edc_pdf_reports/tests/etc/user-salt-restricted.key
edc_pdf_reports/views/__init__.py
edc_pdf_reports/views/pdf_intermediate_view.py
edc_pdf_reports/views/print_pdf_report_view.py
edc_pdf_reports-1.0.2.dist-info/licenses/AUTHORS.rst
edc_pdf_reports-1.0.2.dist-info/licenses/LICENSE
edc_pdf_reports-1.0.2.dist-info/METADATA
edc_pdf_reports-1.0.2.dist-info/WHEEL
edc_pdf_reports-1.0.2.dist-info/top_level.txt
edc_pdf_reports-1.0.2.dist-info/RECORD
