Metadata-Version: 2.4
Name: edc-pdf-reports
Version: 1.0.2
Summary: Report classes using reportlab/pdf for clinicedc/edc projects
Home-page: https://github.com/clinicedc/edc-pdf-reports
Author: Erik van Widenfelt
Author-email: ew2789@gmail.com
License: GPL license, see LICENSE
Keywords: django edc pdf reportlab,clinicedc,clinical trials
Classifier: Environment :: Web Environment
Classifier: Framework :: Django
Classifier: Framework :: Django :: 5.1
Classifier: Intended Audience :: Developers
Classifier: Intended Audience :: Science/Research
Classifier: Operating System :: OS Independent
Classifier: Programming Language :: Python :: 3.12
Classifier: License :: OSI Approved :: GNU General Public License v3 (GPLv3)
Requires-Python: >=3.12
License-File: LICENSE
License-File: AUTHORS.rst
Requires-Dist: beautifulsoup4
Requires-Dist: reportlab
Requires-Dist: inflect
Requires-Dist: pypdf[crypto]
Dynamic: license-file
